sitemap/__init__.py
sitemap/__main__.py
sitemap/sitemap.py
sitemap3-0.0.3.dist-info/DESCRIPTION.rst
sitemap3-0.0.3.dist-info/LICENSE.txt
sitemap3-0.0.3.dist-info/METADATA
sitemap3-0.0.3.dist-info/RECORD
sitemap3-0.0.3.dist-info/WHEEL
sitemap3-0.0.3.dist-info/entry_points.txt
sitemap3-0.0.3.dist-info/metadata.json
sitemap3-0.0.3.dist-info/top_level.txt
tests/__init__.py
tests/test_sitemap.py
