Metadata-Version: 2.0
Name: sitemap3
Version: 0.0.3
Summary: An async command line utility for generating a sitemap within a text file
Home-page: https://github.com/konstantinfarrell/sitemap3
Author: Konstantin Farrell
Author-email: konstantinfarrell@gmail.com
License: MIT
Platform: UNKNOWN
Classifier: Development Status :: 3 - Alpha
Classifier: Environment :: Console
Classifier: Intended Audience :: Developers
Classifier: Intended Audience :: System Administrators
Classifier: License :: OSI Approved :: MIT License
Classifier: Programming Language :: Python :: 3.5
Classifier: Topic :: Utilities
Classifier: Topic :: Internet
Requires-Dist: beautifulsoup4
Requires-Dist: aiohttp
